AUTHORS
LICENSE
MANIFEST.in
README
setup.py
django_valuate.egg-info/PKG-INFO
django_valuate.egg-info/SOURCES.txt
django_valuate.egg-info/dependency_links.txt
django_valuate.egg-info/not-zip-safe
django_valuate.egg-info/top_level.txt
valuate/__init__.py
valuate/admin.py
valuate/forms.py
valuate/management.py
valuate/managers.py
valuate/models.py
valuate/tests.py
valuate/urls.py
valuate/views.py
valuate/templates/valuate/form.html
valuate/templates/valuate/status.html
valuate/templatetags/__init__.py
valuate/templatetags/valuation.py