Metadata-Version: 1.0
Name: django-valuate
Version: 1.0-beta
Summary: A valuation system pluggable to any object
Home-page: http://code.google.com/p/django-valuate/
Author: Rohan Jain
Author-email: dcrodjer@gmail.com
License: BSD
Platform: all
